[{"name":"sprite12","x":2330,"y":147,"width":147,"height":211},{"name":"sprite13","x":402,"y":159,"width":147,"height":226},{"name":"sprite14","x":1381,"y":167,"width":140,"height":218},{"name":"sprite15","x":2317,"y":682,"width":147,"height":226},{"name":"sprite16","x":1366,"y":706,"width":146,"height":211},{"name":"sprite17","x":401,"y":723,"width":148,"height":211},{"name":"sprite18","x":1363,"y":1247,"width":146,"height":218},{"name":"sprite19","x":401,"y":1248,"width":147,"height":233},{"name":"sprite20","x":1368,"y":1789,"width":148,"height":211},{"name":"sprite21","x":412,"y":1794,"width":140,"height":219},{"name":"sprite22","x":403,"y":2328,"width":140,"height":219},{"name":"sprite23","x":1378,"y":2330,"width":148,"height":226}]